cli_help_maker/__init__.py
cli_help_maker/__main__.py
cli_help_maker/generator.py
cli_help_maker/main.py
cli_help_maker/utils.py
cli_help_maker-0.2.0.dist-info/entry_points.txt
cli_help_maker-0.2.0.dist-info/LICENSE
cli_help_maker-0.2.0.dist-info/WHEEL
cli_help_maker-0.2.0.dist-info/METADATA
cli_help_maker-0.2.0.dist-info/RECORD
