Metadata-Version: 2.1
Name: cli-help-maker
Version: 0.2.0
Summary: CLI help message generator. 
Author-email: Agustín Piqueres <agustin.piqueres@gmail.com>
Classifier: Intended Audience :: Developers
Classifier: License :: OSI Approved :: GNU General Public License v3 or later (GPLv3+)
Classifier: Programming Language :: Python :: 3.10
Classifier: Programming Language :: Python :: 3.11
Requires-Dist: nltk>=3.8
Requires-Dist: rich>=12.6.0
Requires-Dist: ruamel.yaml>=0.17.21
Requires-Dist: typer>=0.7.0
Requires-Dist: srsly>=2.4.5
Requires-Dist: pydantic>=1.10.2
Requires-Dist: black ; extra == "dev"
Requires-Dist: mypy ; extra == "dev"
Requires-Dist: isort ; extra == "dev"
Requires-Dist: pytest>=7.2.0 ; extra == "test"
Requires-Dist: pytest-cov>=4.0.0 ; extra == "test"
Requires-Dist: hypothesis>=6.61.0 ; extra == "test"
Requires-Dist: nox>=2022.11.21 ; extra == "test"
Project-URL: Source, https://github.com/plaguss/cli-help-maker
Provides-Extra: dev
Provides-Extra: test
